{
  "generatedAt": "2026-02-26T16:18:21.628Z",
  "baseline": "HEAD:json/migration_metrics.json",
  "delta": {
    "legacyRowCount": {
      "before": 590,
      "after": 590,
      "diff": 0
    },
    "candidateDistinctNameRowCount": {
      "before": 693,
      "after": 693,
      "diff": 0
    },
    "candidateRawSkillCount": {
      "before": 693,
      "after": 693,
      "diff": 0
    },
    "exactMatch": {
      "before": 590,
      "after": 590,
      "diff": 0
    },
    "nameMatchOnly": {
      "before": 0,
      "after": 0,
      "diff": 0
    },
    "unmatchedLegacyRows": {
      "before": 0,
      "after": 0,
      "diff": 0
    },
    "costMismatch": {
      "before": 0,
      "after": 0,
      "diff": 0
    },
    "typeMismatch": {
      "before": 0,
      "after": 0,
      "diff": 0
    },
    "candidateRowsNotInLegacy": {
      "before": 103,
      "after": 103,
      "diff": 0
    },
    "exactMatchRate": {
      "before": 1,
      "after": 1,
      "diff": 0,
      "diffPercentagePoint": 0
    },
    "nameLevelCoverage": {
      "before": 1,
      "after": 1,
      "diff": 0,
      "diffPercentagePoint": 0
    },
    "mismatchRate": {
      "before": 0,
      "after": 0,
      "diff": 0,
      "diffPercentagePoint": 0
    },
    "missingFieldImprovementRate": {
      "before": 1,
      "after": 1,
      "diff": 0,
      "diffPercentagePoint": 0
    },
    "replacementClassification": {
      "replaceable": {
        "before": 590,
        "after": 590,
        "diff": 0
      },
      "needAdditionalImplementation": {
        "before": 0,
        "after": 0,
        "diff": 0
      },
      "nonReplaceable": {
        "before": 0,
        "after": 0,
        "diff": 0
      }
    }
  }
}